{
    "parent": "item/handheld_rod",
    "textures": {
        "layer0": "shroomhearth:item/petrichor_pond_pole_cast"
    },
    "display": {
        "thirdperson_righthand": {
            "rotation": [ 0, 90, 55 ],
            "translation": [ 0, 4.0, 2.5 ],
            "scale": [ 1.009375, 0.85, 0.85 ]
        },
        "thirdperson_lefthand": {
            "rotation": [ 0, -90, -55 ],
            "translation": [ 0, 4.0, 2.5 ],
            "scale": [ 1.009375, 0.85, 0.85 ]
        },
        "firstperson_righthand": {
            "rotation": [ 0, 90, 25 ],
            "translation": [ 0, 1.6, 0.8 ],
            "scale": [ 0.8075, 0.68, 0.68 ]
        },
        "firstperson_lefthand": {
            "rotation": [ 0, -90, -25 ],
            "translation": [ 0, 1.6, 0.8 ],
            "scale": [ 0.8075, 0.68, 0.68 ]
        }
    }
}